formbox.py
formbox-1.0.0.dist-info/entry_points.txt
formbox-1.0.0.dist-info/COPYING
formbox-1.0.0.dist-info/WHEEL
formbox-1.0.0.dist-info/METADATA
formbox-1.0.0.dist-info/RECORD
