Metadata-Version: 2.1
Name: formbox
Version: 1.0.0
Summary: Format mbox as HTML/XML
Keywords: email,format,html,mbox,template,xml
Author-email: Nguyễn Gia Phong <cnx@loang.net>
Maintainer-email: Nguyễn Gia Phong <cnx@loang.net>
Requires-Python: >=3.6
Classifier: Development Status :: 5 - Production/Stable
Classifier: Environment :: Console
Classifier: License :: OSI Approved :: GNU Affero General Public License v3 or later (AGPLv3+)
Classifier: Operating System :: OS Independent
Classifier: Programming Language :: Python
Classifier: Topic :: Communications :: Email
Classifier: Topic :: Utilities
Requires-Dist: mistune
Requires-Dist: nh3
Project-URL: Source, https://trong.loang.net/~cnx/formbox
